coder_evals/__init__.py
coder_evals/agent_harness.py
coder_evals/api_comms.py
coder_evals-0.1.3.dist-info/AUTHORS.rst
coder_evals-0.1.3.dist-info/LICENSE
coder_evals-0.1.3.dist-info/METADATA
coder_evals-0.1.3.dist-info/WHEEL
coder_evals-0.1.3.dist-info/top_level.txt
coder_evals-0.1.3.dist-info/RECORD
