Metadata-Version: 2.1
Name: coder-evals
Version: 0.1.3
Summary: AI Maintainer Agent Harness for our benchmarking and Marketplace API and platform
Home-page: https://github.com/ai-maintainer-inc/coder-evals
Author: AI Maintainer Inc
Author-email: douglas@ai-maintainer.com
License: MIT license
Keywords: coder_evals
Classifier: Development Status :: 2 - Pre-Alpha
Classifier: Intended Audience :: Developers
Classifier: License :: OSI Approved :: MIT License
Classifier: Natural Language :: English
Classifier: Programming Language :: Python :: 3
Classifier: Programming Language :: Python :: 3.8
Classifier: Programming Language :: Python :: 3.9
Classifier: Programming Language :: Python :: 3.10
Requires-Python: >=3.8
License-File: LICENSE
License-File: AUTHORS.rst
Requires-Dist: Click >=7.0
Requires-Dist: aim-platform-sdk >=0.1.3
Requires-Dist: docker >=4.2.2
Requires-Dist: aim-git-util >=0.1.1
